quantum_simulation_recipe/__init__.py
quantum_simulation_recipe/bounds.py
quantum_simulation_recipe/channel.py
quantum_simulation_recipe/fermion.py
quantum_simulation_recipe/measure.py
quantum_simulation_recipe/plot_config.py
quantum_simulation_recipe/spin.py
quantum_simulation_recipe/states.py
quantum_simulation_recipe/trotter.py
quantum_simulation_recipe/utils.py
quantum_simulation_recipe/version.py
quantum_simulation_recipe-0.4.3.dist-info/LICENSE
quantum_simulation_recipe-0.4.3.dist-info/METADATA
quantum_simulation_recipe-0.4.3.dist-info/WHEEL
quantum_simulation_recipe-0.4.3.dist-info/entry_points.txt
quantum_simulation_recipe-0.4.3.dist-info/top_level.txt
quantum_simulation_recipe-0.4.3.dist-info/RECORD
