Metadata-Version: 2.1
Name: quantum-simulation-recipe
Version: 0.4.3
Summary: Recipe for quantum simulation
Home-page: https://github.com/Jue-Xu/quantum-simulation-recipe
Author-email: xujue@connect.hku.hk
License: Apache-2.0
Classifier: Programming Language :: Python :: 3
Classifier: License :: OSI Approved :: Apache Software License
Requires-Python: >=3.10
License-File: LICENSE
Requires-Dist: qiskit>=1.0.2
Requires-Dist: qiskit-aer>=0.17.2
Requires-Dist: jaxlib>=0.6.2
Requires-Dist: jax>=0.6.2
Requires-Dist: openfermion>=1.5.1
Requires-Dist: openfermionpyscf>=0.5
Requires-Dist: matplotlib>=3.8.2
Requires-Dist: numpy>=1.23.5
Requires-Dist: pandas>=2.2.2
Requires-Dist: scipy>=1.12.0
Requires-Dist: colorspace>=1.0.0
Requires-Dist: multiprocess>=0.70.16
